e2eml/__init__.py
e2eml/classification/__init__.py
e2eml/classification/autotuned_nn_classification.py
e2eml/classification/classification_blueprints.py
e2eml/classification/classification_models.py
e2eml/classification/nlp_classification.py
e2eml/full_processing/__init__.py
e2eml/full_processing/cpu_preprocessing.py
e2eml/full_processing/cpu_processing_nlp.py
e2eml/full_processing/postprocessing.py
e2eml/full_processing/preprocessing_blueprints.py
e2eml/model_utils/__init__.py
e2eml/model_utils/deesc_classifier.py
e2eml/model_utils/save_and_load.py
e2eml/model_utils/tabular_gan_for_classification.py
e2eml/model_utils/tabular_gan_for_regression.py
e2eml/model_utils/tabular_gan_training.py
e2eml/post_analysis/segment_finder_classification.py
e2eml/post_analysis/segment_finder_regression.py
e2eml/regression/__init__.py
e2eml/regression/autotuned_nn_regression.py
e2eml/regression/deep_quantile_regression.py
e2eml/regression/nlp_regression.py
e2eml/regression/regression_blueprints.py
e2eml/regression/regression_models.py
e2eml/test/Corona_NLP_train.csv
e2eml/test/NoneShap_feature_importance.png
e2eml/test/ProbaBoost.py
e2eml/test/__init__.py
e2eml/test/classification_blueprints_test.py
e2eml/test/faults.csv
e2eml/test/housingprices_train.csv
e2eml/test/regression_blueprints_test.py
e2eml/test/synthetic_multi_classifcation.csv
e2eml/test/timetravel_static_test.py
e2eml/test/timetravel_walk_test.py
e2eml/test/titanic_train.csv
e2eml/time_series/__init__.py
e2eml/time_series/lstm_model.py
e2eml/time_series/lstm_model_with_quantile_loss.py
e2eml/time_series/rnn_model.py
e2eml/time_series/time_series_blueprints.py
e2eml/time_series/time_series_models.py
e2eml/time_series/time_series_preprocessing.py
e2eml/timetravel/__init__.py
e2eml/timetravel/timetravel.py
e2eml-4.14.20.dist-info/WHEEL
e2eml-4.14.20.dist-info/METADATA
e2eml-4.14.20.dist-info/RECORD
