Metadata-Version: 2.1
Name: e2eml
Version: 4.14.20
Summary: An end-to-end solution for automl
Home-page: https://github.com/ThomasMeissnerDS/e2e_ml
License: GPL-3.0-only
Author: Thomas Meißner
Author-email: meissnercorporation@gmx.de
Requires-Python: >=3.7,<3.10
Classifier: License :: OSI Approved :: GNU General Public License v3 (GPLv3)
Classifier: Programming Language :: Python :: 3
Classifier: Programming Language :: Python :: 3.7
Classifier: Programming Language :: Python :: 3.8
Classifier: Programming Language :: Python :: 3.9
Provides-Extra: full
Provides-Extra: jupyter
Provides-Extra: rapids
Requires-Dist: boostaroota (>=1.3,<2.0)
Requires-Dist: catboost (>=0.21)
Requires-Dist: category_encoders (==2.3.0)
Requires-Dist: cupy (>=8.1.0,<9.0.0); extra == "rapids" or extra == "full"
Requires-Dist: cython (>=0.29.21,<0.30.0); extra == "rapids" or extra == "full"
Requires-Dist: datasets (>=1,<2)
Requires-Dist: dill (>=0.3.3,<0.4.0)
Requires-Dist: imbalanced-learn (>=0.8,<0.9)
Requires-Dist: ipython (>=7.10.0,<8.0.0); extra == "jupyter" or extra == "full"
Requires-Dist: lightgbm (>=3.1.0,<4.0.0)
Requires-Dist: matplotlib (==3.1.3)
Requires-Dist: ngboost (>=0.3.1,<0.4.0)
Requires-Dist: nltk (>=3.2.4,<4.0.0)
Requires-Dist: notebook (>=6.1.0,<7.0.0); extra == "jupyter" or extra == "full"
Requires-Dist: numpy (>=1.19.4,<2.0.0)
Requires-Dist: optuna (>=2.8.0,<3.0.0)
Requires-Dist: pandas (>=1.1.5,<2.0.0)
Requires-Dist: plotly (>=5,<6)
Requires-Dist: psutil (==5.8.0)
Requires-Dist: pytorch_tabnet (>=3.1.1,<4.0.0)
Requires-Dist: scikit-learn (>=1.0.1,<2.0.0)
Requires-Dist: scipy (>=1.5.4,<2.0.0)
Requires-Dist: seaborn (>=0.11.1,<0.12.0)
Requires-Dist: shap (>=0,<1)
Requires-Dist: spacy (>=3.1.0,<4.0.0)
Requires-Dist: textblob (>=0,<1)
Requires-Dist: torch (>=1.7.0,<2.0.0)
Requires-Dist: transformers (>=4,<5)
Requires-Dist: vowpalwabbit (>=8.11.0,<9.0.0)
Requires-Dist: xgboost (>=1.3.3,<2.0.0)
Project-URL: Repository, https://github.com/ThomasMeissnerDS/e2e_ml
